imagevaluec01/__init__.py
imagevaluec01/imagevaluec01.py
imagevaluec01-0.0.3.dist-info/LICENSE.txt
imagevaluec01-0.0.3.dist-info/METADATA
imagevaluec01-0.0.3.dist-info/WHEEL
imagevaluec01-0.0.3.dist-info/top_level.txt
imagevaluec01-0.0.3.dist-info/RECORD
